ramsis2any/__init__.py
ramsis2any/aci_convert.py
ramsis2any/cli.py
ramsis2any/stl_split.py
ramsis2any/templates/ramsis-data.any.jinja
ramsis2any-0.1.0.dist-info/entry_points.txt
ramsis2any-0.1.0.dist-info/WHEEL
ramsis2any-0.1.0.dist-info/METADATA
ramsis2any-0.1.0.dist-info/RECORD
